aiodeepl/__init__.py
aiodeepl/__main__.py
aiodeepl/api.py
aiodeepl/cli.py
aiodeepl/exc.py
aiodeepl-0.1.5.dist-info/LICENSE
aiodeepl-0.1.5.dist-info/METADATA
aiodeepl-0.1.5.dist-info/WHEEL
aiodeepl-0.1.5.dist-info/entry_points.txt
aiodeepl-0.1.5.dist-info/RECORD
